voidfindertk/__init__.py
voidfindertk/io.py
voidfindertk/settings.py
voidfindertk/core/Makefile
voidfindertk/core/__init__.py
voidfindertk/core/box.py
voidfindertk/core/center_finder.py
voidfindertk/core/cleaner.cpp
voidfindertk/core/cleaners.py
voidfindertk/core/plot_acc.py
voidfindertk/core/radius_finder.py
voidfindertk/core/vfinder_abc.py
voidfindertk/core/vgcf.py
voidfindertk/core/voids.py
voidfindertk/core/vsf.py
voidfindertk/datasets/__init__.py
voidfindertk/datasets/spherical_cloud.py
voidfindertk/popcorn/__init__.py
voidfindertk/popcorn/_pc_postprocessing.py
voidfindertk/popcorn/_pc_wrapper.py
voidfindertk/popcorn/_popcorn.py
voidfindertk/svf_popcorn/__init__.py
voidfindertk/svf_popcorn/_svf_pc_postprocessing.py
voidfindertk/svf_popcorn/_svf_pc_wrapper.py
voidfindertk/svf_popcorn/_svf_popcorn.py
voidfindertk/utils/__init__.py
voidfindertk/utils/accabc.py
voidfindertk/utils/box_to_grid.py
voidfindertk/utils/bunch.py
voidfindertk/utils/context_managers.py
voidfindertk/utils/install_assistant.py
voidfindertk/utils/make_workdir.py
voidfindertk/zobov/Makefile
voidfindertk/zobov/__init__.py
voidfindertk/zobov/_zb_postprocessing.py
voidfindertk/zobov/_zb_wrapper.py
voidfindertk/zobov/_zobov.py
voidfindertk/zobov/tracers_in_zones.c
voidfindertk/zobov/tracers_in_zones.so
voidfindertk/zobov/zobov_loader.c
voidfindertk/zobov/zobov_loader.so
voidfindertk/zobov/zones_in_void.c
voidfindertk/zobov/zones_in_void.so
voidfindertk-0.0.1.dist-info/METADATA
voidfindertk-0.0.1.dist-info/WHEEL
voidfindertk-0.0.1.dist-info/top_level.txt
voidfindertk-0.0.1.dist-info/RECORD
