Metadata-Version: 2.4
Name: voidfindertk
Version: 0.0.1
Summary: A package to compare void finders
Author-email: Federico Bustillos <jorgefedericobustillosrava@gmail.com>, Sebastian Gualpa <srgualpa@unc.edu.ar>
License: The MIT License
Project-URL: Repository, https://github.com/FeD7791/voidFinderProject.git
Keywords: void finder,astronomy,large scale structure
Classifier: Development Status :: 2 - Pre-Alpha
Classifier: Intended Audience :: Science/Research
Classifier: Operating System :: OS Independent
Classifier: License :: OSI Approved :: MIT License
Classifier: Programming Language :: Python :: 3.9
Classifier: Programming Language :: Python :: 3.10
Classifier: Programming Language :: Python :: 3.11
Classifier: Programming Language :: Python :: 3.12
Classifier: Programming Language :: Python :: 3.13
Classifier: Topic :: Scientific/Engineering
Requires-Dist: numpy
Requires-Dist: pandas
Requires-Dist: scipy
Requires-Dist: attrs
Requires-Dist: uttrs
Requires-Dist: sh
Requires-Dist: astropy
Requires-Dist: grispy
Requires-Dist: matplotlib
Requires-Dist: seaborn
Requires-Dist: pyyaml
Requires-Dist: joblib
Requires-Dist: py-make
